{
    "title": "Salmon in a Creamy Sauce",
    "ingredients": [
        {
            "name": "lemon",
            "quantity": "6",
            "type": "-"
        },
        {
            "name": "rosemary",
            "quantity": "10",
            "type": "g"
        },
        {
            "name": "thyme",
            "quantity": "10",
            "type": "g"
        },
        {
            "name": "fillets salmon",
            "quantity": "4",
            "type": "-"
        },
        {
            "name": "butter",
            "quantity": "75",
            "type": "g"
        },
        {
            "name": "olive oil",
            "quantity": "3",
            "type": "-"
        },
        {
            "name": "cloves garlic",
            "quantity": "4",
            "type": "-"
        },
        {
            "name": "onion",
            "quantity": "1",
            "type": "-"
        },
        {
            "name": "double cream",
            "quantity": "300",
            "type": "ml"
        },
        {
            "name": "mint",
            "quantity": "1",
            "type": "-"
        }
    ],
    "calories": 0
}