{
    "title": "Easy salmon loaf",
    "ingredients": [
        {
            "name": "salmon flaked",
            "quantity": "1",
            "type": "-"
        },
        {
            "name": "crackers",
            "quantity": "100",
            "type": "g"
        },
        {
            "name": "egg",
            "quantity": "1",
            "type": "-"
        },
        {
            "name": "green pepper",
            "quantity": "1/2",
            "type": "-"
        },
        {
            "name": "onion",
            "quantity": "1/2",
            "type": "-"
        },
        {
            "name": "milk",
            "quantity": "4",
            "type": "-"
        },
        {
            "name": "sauce",
            "quantity": "1/2",
            "type": "teaspoon"
        },
        {
            "name": "pepper sauce",
            "quantity": "1",
            "type": "-"
        },
        {
            "name": "pepper",
            "quantity": 1,
            "type": "-"
        }
    ],
    "calories": 0
}