{
    "title": "Aubergine and spinach lasagne",
    "ingredients": [
        {
            "name": "aubergine",
            "quantity": "1",
            "type": "-"
        },
        {
            "name": "spinach",
            "quantity": "250",
            "type": "g"
        },
        {
            "name": "cheese",
            "quantity": "1",
            "type": "-"
        },
        {
            "name": "pasta sauce",
            "quantity": "1",
            "type": "-"
        },
        {
            "name": "lasagne",
            "quantity": "1",
            "type": "-"
        },
        {
            "name": "tomatoes",
            "quantity": "3",
            "type": "-"
        },
        {
            "name": "mozzarella cheese",
            "quantity": "1",
            "type": "-"
        },
        {
            "name": "parsley",
            "quantity": 1,
            "type": "-"
        },
        {
            "name": "salt pepper",
            "quantity": 1,
            "type": "-"
        }
    ],
    "calories": 0
}