{
    "title": "Creamy potato and celery soup",
    "ingredients": [
        {
            "name": "bunch celery",
            "quantity": "1",
            "type": "-"
        },
        {
            "name": "potato",
            "quantity": "1",
            "type": "-"
        },
        {
            "name": "onion",
            "quantity": "1",
            "type": "-"
        },
        {
            "name": "celery salt",
            "quantity": "1/2",
            "type": "teaspoon"
        },
        {
            "name": "chicken stock",
            "quantity": "1.5L",
            "type": "-"
        },
        {
            "name": "oil",
            "quantity": "1",
            "type": "-"
        }
    ],
    "calories": 0
}