{
    "title": "Cinnamon-Spiced Fudge",
    "ingredients": [
        {
            "name": "icing sugar",
            "quantity": "360",
            "type": "g"
        },
        {
            "name": "cocoa powder",
            "quantity": "50",
            "type": "g"
        },
        {
            "name": "cinnamon",
            "quantity": "1-2",
            "type": "-"
        },
        {
            "name": "butter",
            "quantity": "125",
            "type": "g"
        },
        {
            "name": "milk",
            "quantity": "4",
            "type": "-"
        },
        {
            "name": "vanilla",
            "quantity": "1",
            "type": "teaspoon"
        }
    ],
    "calories": 0
}