{
    "title": "Crustless aubergine, red pepper and sheep's feta tart",
    "ingredients": [
        {
            "name": "sheeps feta",
            "quantity": "400",
            "type": "g"
        },
        {
            "name": "garlic minced olive oil",
            "quantity": "1",
            "type": "-"
        },
        {
            "name": "",
            "quantity": "200",
            "type": "g"
        },
        {
            "name": "peppers",
            "quantity": "4",
            "type": "-"
        },
        {
            "name": "aubergines",
            "quantity": "4",
            "type": "-"
        },
        {
            "name": "eggs",
            "quantity": "2",
            "type": "-"
        },
        {
            "name": "pesto",
            "quantity": 1,
            "type": "-"
        },
        {
            "name": "basil",
            "quantity": "125",
            "type": "g"
        },
        {
            "name": "pine nuts",
            "quantity": "5",
            "type": "tbsp"
        },
        {
            "name": "clove garlic",
            "quantity": "1",
            "type": "-"
        },
        {
            "name": "pepper",
            "quantity": 1,
            "type": "-"
        },
        {
            "name": "olive oil",
            "quantity": "2",
            "type": "-"
        }
    ],
    "calories": 0
}