{
    "title": "Venison Stuffed Acorn Squash",
    "ingredients": [
        {
            "name": "rice",
            "quantity": "55",
            "type": "g"
        },
        {
            "name": "water",
            "quantity": "625",
            "type": "ml"
        },
        {
            "name": "acorn squash",
            "quantity": "1",
            "type": "-"
        },
        {
            "name": "",
            "quantity": "30",
            "type": "g"
        },
        {
            "name": "minced venison",
            "quantity": "225",
            "type": "g"
        },
        {
            "name": "sugar",
            "quantity": "110",
            "type": "g"
        },
        {
            "name": "cinnamon",
            "quantity": "1",
            "type": "teaspoon"
        },
        {
            "name": "nutmeg",
            "quantity": "1/2",
            "type": "teaspoon"
        },
        {
            "name": "salt pepper",
            "quantity": 1,
            "type": "-"
        },
        {
            "name": "butter",
            "quantity": "50",
            "type": "g"
        }
    ],
    "calories": 0
}