{
    "title": "Five minute chocolate breakfast muffins",
    "ingredients": [
        {
            "name": "flour",
            "quantity": "4",
            "type": "-"
        },
        {
            "name": "sugar",
            "quantity": "4",
            "type": "-"
        },
        {
            "name": "cocoa powder",
            "quantity": "2",
            "type": "-"
        },
        {
            "name": "baking powder",
            "quantity": "1/3",
            "type": "teaspoon"
        },
        {
            "name": "chocolate",
            "quantity": "2",
            "type": "-"
        },
        {
            "name": "egg",
            "quantity": "2",
            "type": "-"
        },
        {
            "name": "milk",
            "quantity": "3",
            "type": "-"
        },
        {
            "name": "sunflower oil",
            "quantity": "3",
            "type": "-"
        },
        {
            "name": "vanilla",
            "quantity": "1",
            "type": "-"
        }
    ],
    "calories": 0
}