{
    "title": "Tandoori chicken drumsticks",
    "ingredients": [
        {
            "name": "chicken drumsticks",
            "quantity": "8",
            "type": "-"
        },
        {
            "name": "salt",
            "quantity": "1",
            "type": "teaspoon"
        },
        {
            "name": "lemon juiced",
            "quantity": "1",
            "type": "-"
        },
        {
            "name": "yogurt",
            "quantity": "2",
            "type": "-"
        },
        {
            "name": "onion",
            "quantity": "1/2",
            "type": "-"
        },
        {
            "name": "garlic clove",
            "quantity": "1",
            "type": "-"
        },
        {
            "name": "root ginger",
            "quantity": "1",
            "type": "-"
        },
        {
            "name": "green",
            "quantity": "2",
            "type": "-"
        },
        {
            "name": "masala",
            "quantity": "2",
            "type": "-"
        },
        {
            "name": "turmeric",
            "quantity": "1",
            "type": "teaspoon"
        },
        {
            "name": "tandoori powder paste",
            "quantity": "2",
            "type": "-"
        }
    ],
    "calories": 0
}