{
    "title": "Chocolate Peanut Butter Cake",
    "ingredients": [
        {
            "name": "flour",
            "quantity": "375",
            "type": "g"
        },
        {
            "name": "",
            "quantity": "2",
            "type": "-"
        },
        {
            "name": "salt",
            "quantity": "1",
            "type": "teaspoon"
        },
        {
            "name": "cocoa powder",
            "quantity": "6",
            "type": "-"
        },
        {
            "name": "caster sugar",
            "quantity": "400",
            "type": "g"
        },
        {
            "name": "butter",
            "quantity": "150",
            "type": "g"
        },
        {
            "name": "vinegar",
            "quantity": "2",
            "type": "-"
        },
        {
            "name": "water",
            "quantity": "475",
            "type": "ml"
        },
        {
            "name": "peanut butter",
            "quantity": "4",
            "type": "-"
        },
        {
            "name": "sugar",
            "quantity": "220",
            "type": "g"
        },
        {
            "name": "milk",
            "quantity": "4",
            "type": "-"
        },
        {
            "name": "butter",
            "quantity": "50",
            "type": "g"
        }
    ],
    "calories": 0
}