{
    "title": "Simple flapjack",
    "ingredients": [
        {
            "name": "butter",
            "quantity": "110",
            "type": "g"
        },
        {
            "name": "sugar",
            "quantity": "40",
            "type": "g"
        },
        {
            "name": "syrup",
            "quantity": "2",
            "type": "-"
        },
        {
            "name": "porridge oats",
            "quantity": "175",
            "type": "g"
        },
        {
            "name": "sultanas raisins",
            "quantity": "50",
            "type": "g"
        },
        {
            "name": "chocolate",
            "quantity": "150",
            "type": "g"
        }
    ],
    "calories": 0
}