{
    "title": "Puff pastry quiche Lorraine",
    "ingredients": [
        {
            "name": "pastry",
            "quantity": "1",
            "type": "-"
        },
        {
            "name": "eggs",
            "quantity": "3",
            "type": "-"
        },
        {
            "name": "milk",
            "quantity": "300",
            "type": "ml"
        },
        {
            "name": "double cream",
            "quantity": "200",
            "type": "ml"
        },
        {
            "name": "bacon",
            "quantity": "200",
            "type": "g"
        },
        {
            "name": "cheese",
            "quantity": "200",
            "type": "g"
        },
        {
            "name": "salt pepper",
            "quantity": 1,
            "type": "-"
        }
    ],
    "calories": 0
}