{
    "title": "Hungarian-style meatballs",
    "ingredients": [
        {
            "name": "butter",
            "quantity": "30",
            "type": "g"
        },
        {
            "name": "onion",
            "quantity": "1",
            "type": "-"
        },
        {
            "name": "mushrooms",
            "quantity": "340",
            "type": "g"
        },
        {
            "name": "minced turkey",
            "quantity": "340",
            "type": "g"
        },
        {
            "name": "breadcrumbs",
            "quantity": "50",
            "type": "g"
        },
        {
            "name": "egg",
            "quantity": "1",
            "type": "-"
        },
        {
            "name": "parsley",
            "quantity": "2",
            "type": "tbsp"
        },
        {
            "name": "potatoes",
            "quantity": "550",
            "type": "g"
        },
        {
            "name": "salt pepper",
            "quantity": 1,
            "type": "-"
        },
        {
            "name": "yogurt",
            "quantity": "4",
            "type": "tbsp"
        },
        {
            "name": "parsley garnish",
            "quantity": 1,
            "type": "-"
        },
        {
            "name": "pepper sauce",
            "quantity": 1,
            "type": "-"
        },
        {
            "name": "olive oil",
            "quantity": "2",
            "type": "tbsp"
        },
        {
            "name": "onion",
            "quantity": "1",
            "type": "-"
        },
        {
            "name": "garlic cloves",
            "quantity": "2",
            "type": "-"
        },
        {
            "name": "pepper",
            "quantity": "1",
            "type": "-"
        },
        {
            "name": "green pepper",
            "quantity": "1",
            "type": "-"
        },
        {
            "name": "paprika",
            "quantity": "1",
            "type": "tbsp"
        },
        {
            "name": "",
            "quantity": "1",
            "type": "-"
        },
        {
            "name": "pinch caraway",
            "quantity": 1,
            "type": "-"
        }
    ],
    "calories": 0
}