{
    "title": "Easy chocolate buttercream icing",
    "ingredients": [
        {
            "name": "margarine",
            "quantity": "55",
            "type": "g"
        },
        {
            "name": "icing sugar",
            "quantity": "55",
            "type": "g"
        },
        {
            "name": "vanilla",
            "quantity": "1",
            "type": "-"
        },
        {
            "name": "cocoa powder",
            "quantity": "2",
            "type": "-"
        }
    ],
    "calories": 0
}