{
    "title": "Potato pie with sausage and cheese",
    "ingredients": [
        {
            "name": "potatoes",
            "quantity": "750",
            "type": "g"
        },
        {
            "name": "olive oil",
            "quantity": "1",
            "type": "teaspoon"
        },
        {
            "name": "onion",
            "quantity": "1",
            "type": "-"
        },
        {
            "name": "sausages",
            "quantity": "400",
            "type": "g"
        },
        {
            "name": "milk",
            "quantity": "100",
            "type": "ml"
        },
        {
            "name": "cheese",
            "quantity": "50",
            "type": "g"
        },
        {
            "name": "wholegrain mustard",
            "quantity": "1",
            "type": "teaspoon"
        },
        {
            "name": "tomatoes",
            "quantity": "2",
            "type": "-"
        }
    ],
    "calories": 0
}