{
    "title": "Rhubarb and almond cake",
    "ingredients": [
        {
            "name": "rhubarb",
            "quantity": "4",
            "type": "-"
        },
        {
            "name": "margarine temperature",
            "quantity": "140",
            "type": "g"
        },
        {
            "name": "caster sugar",
            "quantity": "150",
            "type": "g"
        },
        {
            "name": "eggs",
            "quantity": "2",
            "type": "-"
        },
        {
            "name": "vanilla",
            "quantity": "1",
            "type": "teaspoon"
        },
        {
            "name": "zest lemon",
            "quantity": 1,
            "type": "-"
        },
        {
            "name": "raising flour",
            "quantity": "110",
            "type": "g"
        },
        {
            "name": "almonds",
            "quantity": "200",
            "type": "g"
        },
        {
            "name": "baking powder",
            "quantity": "1",
            "type": "-"
        },
        {
            "name": "cinnamon",
            "quantity": "1",
            "type": "teaspoon"
        },
        {
            "name": "flaked almonds",
            "quantity": "2",
            "type": "-"
        }
    ],
    "calories": 0
}