{
    "title": "Chocolate beetroot loaf cake",
    "ingredients": [
        {
            "name": "butter",
            "quantity": "175",
            "type": "g"
        },
        {
            "name": "caster sugar",
            "quantity": "200",
            "type": "g"
        },
        {
            "name": "eggs",
            "quantity": "3",
            "type": "-"
        },
        {
            "name": "raising flour",
            "quantity": "175",
            "type": "g"
        },
        {
            "name": "baking powder",
            "quantity": "1",
            "type": "teaspoon"
        },
        {
            "name": "milk",
            "quantity": "110",
            "type": "ml"
        },
        {
            "name": "cocoa powder",
            "quantity": "85",
            "type": "g"
        },
        {
            "name": "vanilla",
            "quantity": "1",
            "type": "teaspoon"
        },
        {
            "name": "beetroot",
            "quantity": "110",
            "type": "g"
        },
        {
            "name": "chocolate",
            "quantity": "55",
            "type": "g"
        }
    ],
    "calories": 0
}