{
    "title": "Chocolate Christmas logs",
    "ingredients": [
        {
            "name": "",
            "quantity": 1,
            "type": "-"
        },
        {
            "name": "butter",
            "quantity": "150",
            "type": "g"
        },
        {
            "name": "caster sugar",
            "quantity": "150",
            "type": "g"
        },
        {
            "name": "eggs",
            "quantity": "3",
            "type": "-"
        },
        {
            "name": "raising flour",
            "quantity": "150",
            "type": "g"
        },
        {
            "name": "cocoa powder",
            "quantity": "40",
            "type": "g"
        },
        {
            "name": "icing",
            "quantity": 1,
            "type": "-"
        },
        {
            "name": "icing sugar",
            "quantity": "2",
            "type": "-"
        },
        {
            "name": "water",
            "quantity": "2",
            "type": "-"
        },
        {
            "name": "",
            "quantity": "3",
            "type": "-"
        }
    ],
    "calories": 0
}