{
    "title": "Fennel carpaccio with balsamic vinaigrette",
    "ingredients": [
        {
            "name": "fennel",
            "quantity": "100",
            "type": "g"
        },
        {
            "name": "pecan nuts",
            "quantity": "30",
            "type": "g"
        },
        {
            "name": "orange",
            "quantity": "1/4",
            "type": "-"
        },
        {
            "name": "",
            "quantity": 1,
            "type": "-"
        },
        {
            "name": "orange juice",
            "quantity": "2",
            "type": "-"
        },
        {
            "name": "orange zest",
            "quantity": "1/2",
            "type": "teaspoon"
        },
        {
            "name": "sweet vinegar",
            "quantity": "1",
            "type": "-"
        },
        {
            "name": "olive oil",
            "quantity": "1",
            "type": "-"
        },
        {
            "name": "cumin",
            "quantity": 1,
            "type": "-"
        },
        {
            "name": "fennel greens",
            "quantity": 1,
            "type": "-"
        },
        {
            "name": "salt",
            "quantity": 1,
            "type": "-"
        }
    ],
    "calories": 0
}