{
    "title": "Split pea soup with sausage and pancetta",
    "ingredients": [
        {
            "name": "water",
            "quantity": "2L",
            "type": "-"
        },
        {
            "name": "chicken vegtable stock",
            "quantity": "3",
            "type": "-"
        },
        {
            "name": "green peas",
            "quantity": "500",
            "type": "g"
        },
        {
            "name": "",
            "quantity": "1",
            "type": "-"
        },
        {
            "name": "onion",
            "quantity": "1",
            "type": "-"
        },
        {
            "name": "leeks",
            "quantity": "2",
            "type": "-"
        },
        {
            "name": "celery",
            "quantity": "3",
            "type": "-"
        },
        {
            "name": "carrots",
            "quantity": "400",
            "type": "g"
        },
        {
            "name": "bunch parsley",
            "quantity": "1",
            "type": "-"
        },
        {
            "name": "sausage",
            "quantity": "1",
            "type": "-"
        },
        {
            "name": "smoked sausage",
            "quantity": "1",
            "type": "-"
        },
        {
            "name": "pancetta",
            "quantity": "200",
            "type": "g"
        },
        {
            "name": "salt pepper",
            "quantity": 1,
            "type": "-"
        }
    ],
    "calories": 0
}