{
    "title": "Chocolate and banana cake",
    "ingredients": [
        {
            "name": "flour",
            "quantity": "275",
            "type": "g"
        },
        {
            "name": "baking powder",
            "quantity": "1",
            "type": "teaspoon"
        },
        {
            "name": "salt",
            "quantity": "1",
            "type": "teaspoon"
        },
        {
            "name": "",
            "quantity": "3/4",
            "type": "teaspoon"
        },
        {
            "name": "cocoa powder",
            "quantity": "30",
            "type": "g"
        },
        {
            "name": "butter temperature",
            "quantity": "175",
            "type": "g"
        },
        {
            "name": "caster sugar",
            "quantity": "300",
            "type": "g"
        },
        {
            "name": "eggs temperature",
            "quantity": "2",
            "type": "-"
        },
        {
            "name": "vanilla",
            "quantity": "1",
            "type": "teaspoon"
        },
        {
            "name": "bananas",
            "quantity": "225",
            "type": "g"
        },
        {
            "name": "buttermilk",
            "quantity": "120",
            "type": "ml"
        },
        {
            "name": "cream cheese",
            "quantity": "100",
            "type": "g"
        },
        {
            "name": "butter",
            "quantity": "45",
            "type": "g"
        },
        {
            "name": "vanilla",
            "quantity": "1",
            "type": "teaspoon"
        },
        {
            "name": "icing sugar",
            "quantity": "250",
            "type": "g"
        },
        {
            "name": "cocoa powder",
            "quantity": "20",
            "type": "g"
        },
        {
            "name": "milk",
            "quantity": "2",
            "type": "-"
        },
        {
            "name": "bananas",
            "quantity": 1,
            "type": "-"
        }
    ],
    "calories": 0
}