{
    "title": "Cajun prawn and crab jambalaya",
    "ingredients": [
        {
            "name": "vegetable oil",
            "quantity": "1",
            "type": "tbsp"
        },
        {
            "name": "onions",
            "quantity": "2",
            "type": "-"
        },
        {
            "name": "green pepper",
            "quantity": "1",
            "type": "-"
        },
        {
            "name": "celery",
            "quantity": "2",
            "type": "-"
        },
        {
            "name": "gammon",
            "quantity": "100",
            "type": "g"
        },
        {
            "name": "flour",
            "quantity": "1",
            "type": "tbsp"
        },
        {
            "name": "tomatoes",
            "quantity": "2",
            "type": "-"
        },
        {
            "name": "chicken fish stock",
            "quantity": "500",
            "type": "ml"
        },
        {
            "name": "rice",
            "quantity": "300",
            "type": "g"
        },
        {
            "name": "seasoning",
            "quantity": "2",
            "type": "-"
        },
        {
            "name": "tiger prawns",
            "quantity": "250",
            "type": "g"
        },
        {
            "name": "crab meat",
            "quantity": "170",
            "type": "g"
        },
        {
            "name": "coriander",
            "quantity": "2",
            "type": "tbsp"
        }
    ],
    "calories": 0
}