{
    "title": "Apricot glazed roast ham",
    "ingredients": [
        {
            "name": "gammon",
            "quantity": "1",
            "type": "-"
        },
        {
            "name": "cloves",
            "quantity": "4",
            "type": "-"
        },
        {
            "name": "apricot jam compote",
            "quantity": "8",
            "type": "-"
        },
        {
            "name": "honey",
            "quantity": "1",
            "type": "-"
        },
        {
            "name": "mustard",
            "quantity": "2",
            "type": "-"
        }
    ],
    "calories": 0
}