{
    "title": "Dobos Torte",
    "ingredients": [
        {
            "name": "egg",
            "quantity": "9",
            "type": "-"
        },
        {
            "name": "caster sugar",
            "quantity": "200",
            "type": "g"
        },
        {
            "name": "egg",
            "quantity": "8",
            "type": "-"
        },
        {
            "name": "milk",
            "quantity": "4",
            "type": "-"
        },
        {
            "name": "lemon zest",
            "quantity": "1",
            "type": "-"
        },
        {
            "name": "vanilla",
            "quantity": "1",
            "type": "-"
        },
        {
            "name": "pinch salt",
            "quantity": "1",
            "type": "-"
        },
        {
            "name": "flour",
            "quantity": "200",
            "type": "g"
        },
        {
            "name": "butter",
            "quantity": "10",
            "type": "g"
        },
        {
            "name": "caster sugar",
            "quantity": "200",
            "type": "g"
        },
        {
            "name": "recipe",
            "quantity": "1",
            "type": "-"
        }
    ],
    "calories": 0
}