{
    "title": "Eggless chocolate cake",
    "ingredients": [
        {
            "name": "flour",
            "quantity": "375",
            "type": "g"
        },
        {
            "name": "caster sugar",
            "quantity": "375",
            "type": "g"
        },
        {
            "name": "salt",
            "quantity": "1",
            "type": "teaspoon"
        },
        {
            "name": "",
            "quantity": "2",
            "type": "-"
        },
        {
            "name": "cocoa powder",
            "quantity": "45",
            "type": "g"
        },
        {
            "name": "vegetable oil",
            "quantity": "180",
            "type": "ml"
        },
        {
            "name": "vinegar",
            "quantity": "2",
            "type": "-"
        },
        {
            "name": "vanilla",
            "quantity": "2",
            "type": "-"
        },
        {
            "name": "water",
            "quantity": "500",
            "type": "ml"
        }
    ],
    "calories": 0
}