{
    "title": "Badam (almond) sherbet",
    "ingredients": [
        {
            "name": "milk",
            "quantity": "500",
            "type": "ml"
        },
        {
            "name": "double cream",
            "quantity": "2",
            "type": "-"
        },
        {
            "name": "almonds",
            "quantity": "140",
            "type": "g"
        },
        {
            "name": "icing sugar",
            "quantity": "60",
            "type": "g"
        },
        {
            "name": "rose water",
            "quantity": "2",
            "type": "-"
        }
    ],
    "calories": 0
}