{
    "title": "Balsamic-glazed salmon fillets",
    "ingredients": [
        {
            "name": "olive oil",
            "quantity": "1",
            "type": "-"
        },
        {
            "name": "cloves garlic minced",
            "quantity": "4",
            "type": "-"
        },
        {
            "name": "wine",
            "quantity": "1",
            "type": "-"
        },
        {
            "name": "honey",
            "quantity": "1",
            "type": "-"
        },
        {
            "name": "vinegar",
            "quantity": "85",
            "type": "ml"
        },
        {
            "name": "mustard",
            "quantity": "2",
            "type": "-"
        },
        {
            "name": "salt pepper",
            "quantity": 1,
            "type": "-"
        },
        {
            "name": "oregano",
            "quantity": "1",
            "type": "-"
        },
        {
            "name": "salmon fillets",
            "quantity": "6",
            "type": "-"
        }
    ],
    "calories": 0
}